lsmmdma/__init__.py
lsmmdma/initializers.py
lsmmdma/main.py
lsmmdma/metrics.py
lsmmdma/mmdma_functions.py
lsmmdma/train.py
lsmmdma/version.py
lsmmdma/data/__init__.py
lsmmdma/data/checkpointer.py
lsmmdma/data/data_pipeline.py
lsmmdma-0.1.11.dist-info/LICENSE
lsmmdma-0.1.11.dist-info/METADATA
lsmmdma-0.1.11.dist-info/WHEEL
lsmmdma-0.1.11.dist-info/top_level.txt
lsmmdma-0.1.11.dist-info/RECORD
