Metadata-Version: 2.1
Name: lsmmdma
Version: 0.1.11
Summary: Scaling MMD-MA.
Home-page: https://github.com/google-research/large_scale_mmdma
Author: Google LLC
Author-email: no-reply@google.com
License: Apache 2.0
Keywords: kernel,data integration
Classifier: Intended Audience :: Science/Research
Classifier: Topic :: Scientific/Engineering :: Artificial Intelligence
Classifier: Programming Language :: Python :: 3
Classifier: License :: OSI Approved :: Apache Software License
License-File: LICENSE
Requires-Dist: absl-py
Requires-Dist: numpy
Requires-Dist: torch (>=1.10)
Requires-Dist: tensorflow-cpu (>=2.8)
Requires-Dist: pykeops
Requires-Dist: typing
Requires-Dist: dataclasses
Requires-Dist: cmake (==3.18)
Requires-Dist: setuptools (==59.5.0)
Requires-Dist: tenacity
Requires-Dist: sklearn
Requires-Dist: scanpy
Requires-Dist: scipy
